hands/__init__.py
hands/main.py
hands/Models/cube_renderer.py
hands/packages/gestures.py
hands/packages/hand_landmarks.py
hands/packages/shared_state.py
hand3d-0.3.0.dist-info/METADATA
hand3d-0.3.0.dist-info/WHEEL
hand3d-0.3.0.dist-info/entry_points.txt
hand3d-0.3.0.dist-info/top_level.txt
hand3d-0.3.0.dist-info/RECORD
