Metadata-Version: 2.4
Name: hand3d
Version: 0.3.0
Summary: Hand-Aided Navigation for Dimensions. Hand tracking app using MediaPipe, OpenCV, and Pygame
Requires-Python: >=3.11
Requires-Dist: mediapipe==0.10.5
Requires-Dist: opencv-python
Requires-Dist: pygame
Requires-Dist: PyOpenGL
Requires-Dist: PyOpenGL_accelerate
